chelodina/__init__.py
chelodina/__main__.py
chelodina/ast_builder.py
chelodina/compiler.py
chelodina/lexer.py
chelodina/parser.py
chelodina/utils/__init__.py
chelodina/utils/debug.py
chelodina/utils/validator.py
chelodina-0.5.5.dist-info/METADATA
chelodina-0.5.5.dist-info/RECORD
chelodina-0.5.5.dist-info/WHEEL
chelodina-0.5.5.dist-info/entry_points.txt
chelodina-0.5.5.dist-info/top_level.txt
tests/__init__.py
tests/test_compiler.py
