Metadata-Version: 2.1
Name: chelodina
Version: 0.5.5
Summary: A Logo to Python transpiler
Home-page: http://github.com/pablasso/chelodina
Author: Juan Pablo Ortiz
Author-email: me@pablasso.com
License: MIT
Platform: UNKNOWN
Requires-Dist: ply
Requires-Dist: astor
